cad2vox/__init__.py
cad2vox/main.py
cad2vox/utill.py
cad2vox-1.7.3.dist-info/LICENSE
cad2vox-1.7.3.dist-info/METADATA
cad2vox-1.7.3.dist-info/WHEEL
cad2vox-1.7.3.dist-info/top_level.txt
cad2vox-1.7.3.dist-info/RECORD
