Metadata-Version: 2.1
Name: cad2vox
Version: 1.7.3
Summary: A python library to provide the user interface for the CudaVox library
Home-page: https://github.com/bjthorpe/Cad2vox
Author: Ben Thorpe
Author-email: b.j.thorpe@swansea.ac.uk
Classifier: Programming Language :: Python :: 3
Classifier: License :: OSI Approved :: MIT License
Classifier: Operating System :: POSIX :: Linux
Requires-Python: >=3.6
License-File: LICENSE
Requires-Dist: CudaVox (>=1.7)
Requires-Dist: numpy (>=1.19)
Requires-Dist: meshio
Requires-Dist: tifffile
Requires-Dist: pillow (>=8.3)
Requires-Dist: pandas
Requires-Dist: cmake (>=3.22.0)
Requires-Dist: pybind11
